meshagent/duckdb/agents/__init__.py
meshagent/duckdb/agents/indexer.py
meshagent/duckdb/tools/__init__.py
meshagent/duckdb/tools/tables.py
meshagent_duckdb-0.0.1.dist-info/METADATA
meshagent_duckdb-0.0.1.dist-info/WHEEL
meshagent_duckdb-0.0.1.dist-info/top_level.txt
meshagent_duckdb-0.0.1.dist-info/RECORD
