Metadata-Version: 2.2
Name: meshagent-duckdb
Version: 0.0.1
Summary: Duckdb support for Meshagent
Home-page: 
License: MIT
Project-URL: Documentation, https://meshagent.com
Project-URL: Website, https://meshagent.com
Project-URL: Source, https://github.com/meshagent
Requires-Python: >=3.9.0
Requires-Dist: pytest>=8.3.4
Requires-Dist: pytest-asyncio>=0.24.0
Requires-Dist: meshagent-api>=0.0.1
Requires-Dist: meshagent-agents>=0.0.1
Requires-Dist: meshagent-tools>=0.0.1
Requires-Dist: pandas>=2.1.0
Requires-Dist: duckdb>=1.1.3
Requires-Dist: pyarrow>=19.0.0
Dynamic: description-content-type
Dynamic: license
Dynamic: project-url
Dynamic: requires-dist
Dynamic: requires-python
Dynamic: summary
